{"file":"useSubcat-DziHAppG.js","mappings":";;AAGO,SAAS,YAAY;AAC1B,QAAM,EAAE,KAAM,IAAG,WAAY;AAC7B,QAAM,SAAS,mBAAmB,OAAO;AAEzC,QAAM,UAAU,IAAI,EAAE;AAGtB,QAAM,qBAAqB,OAAO,QAAQ,OAAO;AAG/C,QAAI;AAEF,YAAM,SAAS,CAEd;AAED,UAAI,WAAW;AAEf,UAAI,OAAO;AACT,eAAO,QAAQ;AACrB,gBAAQ;AACR,mBAAW,MAAM,KAAK,IAAI,GAAG,MAAM,wBAAwB,KAAK,IAAI,EAAE,QAAQ;AAAA,MACzE,OACA;AACL,gBAAO;AACP,mBAAW,MAAM,KAAK,IAAI,GAAG,MAAM,wBAAwB,EAAE,QAAQ;AAAA,MACnE;AAEE,cAAQ,QAAQ,SAAS,KAAK;AAAA,IAC/B,SAAQ,OAAO;AACd,cAAQ,MAAM,iCAAiC,MAAM,WAAW,MAAM,SAAS,OAAO,MAAM,OAAO;AAAA,IACpG;AAAA,EACF;AAID,SAAO;AAAA,IACL;AAAA,IACA;AAAA,EACD;AACH;","names":[],"sources":["../../../../composables/useSubcat.js"],"sourcesContent":["import { ref, computed } from 'vue'\r\nimport { useRuntimeConfig, useNuxtApp } from '#imports'\r\n\r\nexport function useSubcat() {\r\n  const { $api } = useNuxtApp()\r\n  const apiUrl = useRuntimeConfig().public.apiBaseUrl\r\n\r\n  const subcats = ref([])\r\n\r\n\r\n  const fetchSubcatsCommon = async (catid = '') => {\r\n\t \r\n\t  \r\n    try {\r\n      // Build the query parameters\r\n      const params = {\r\n\r\n      }\r\n\r\n      let response = ''\r\n      // Include catid if provided\r\n      if (catid) {\r\n        params.catid = catid\r\n\t\tcatid = catid\r\n\t\tresponse = await $api.get(`${apiUrl}/admin/subcat/common/${catid}`, { params })\r\n      }\r\n\t  else{\r\n\t\tcatid =''\r\n\t\tresponse = await $api.get(`${apiUrl}/admin/subcat/common`, { params })\r\n\t  }\r\n      \r\n      subcats.value = response.data.data\r\n    } catch (error) {\r\n      console.error('Error fetching subcategories:', error.response ? error.response.data : error.message)\r\n    }\r\n  }\r\n\r\n\r\n\r\n  return {\r\n    subcats,\r\n    fetchSubcatsCommon,\r\n  }\r\n}\r\n"],"version":3}